seq_toolkit/__init__.py
seq_toolkit-0.0.21.dist-info/LICENSE
seq_toolkit-0.0.21.dist-info/METADATA
seq_toolkit-0.0.21.dist-info/WHEEL
seq_toolkit-0.0.21.dist-info/top_level.txt
seq_toolkit-0.0.21.dist-info/RECORD
