Metadata-Version: 2.1
Name: seq-toolkit
Version: 0.0.21
Summary: seq-toolkit - Basic sequence manipulation tools. A vintools package.
Home-page: UNKNOWN
Author: Michael E. Vinyard - Harvard University - Massachussetts General Hospital - Broad Institute of MIT and Harvard
Author-email: mvinyard@broadinstitute.org
License: MIT
Platform: UNKNOWN
Classifier: Development Status :: 2 - Pre-Alpha
Classifier: Programming Language :: Python :: 3.7
Classifier: Intended Audience :: Science/Research
Classifier: Topic :: Scientific/Engineering :: Bio-Informatics
Requires-Python: >3.7.0
License-File: LICENSE
Requires-Dist: vinplots (>=0.0.1)
Requires-Dist: pandas (>=1.3.3)
